pyfuncpatmatch/__init__.py
pyfuncpatmatch/__main__.py
pyfuncpatmatch/__version__.py
pyfuncpatmatch/pm.py
pyfuncpatmatch/pm_ext.py
pyfuncpatmatch/pm_utils.py
pyfuncpatmatch-0.1.0.dist-info/WHEEL
pyfuncpatmatch-0.1.0.dist-info/METADATA
pyfuncpatmatch-0.1.0.dist-info/RECORD
